lahar.py
lahar_python-0.1.0.dist-info/LICENSE
lahar_python-0.1.0.dist-info/METADATA
lahar_python-0.1.0.dist-info/WHEEL
lahar_python-0.1.0.dist-info/top_level.txt
lahar_python-0.1.0.dist-info/RECORD
