Metadata-Version: 2.1
Name: lahar-python
Version: 0.1.0
Summary: LAHAR API integration wrapper for python
Home-page: http://github.com/virb30/lahar-python/
Author: Vinícius Bôscoa
Author-email: virb30@gmail.com
License: MIT
Project-URL: Bug Tracker, http://github.com/virb30/lahar-python/issues
Platform: any
Classifier: Development Status :: 5 - Production/Stable
Classifier: Intended Audience :: Developers
Classifier: License :: OSI Approved :: MIT License
Classifier: Natural Language :: Portuguese
Classifier: Operating System :: OS Independent
Classifier: Programming Language :: Python
Classifier: Programming Language :: Python :: 3
Classifier: Topic :: Software Development :: Libraries
Requires-Python: >=3.6
License-File: LICENSE
Requires-Dist: requests
